slack_notifier_airflow/__init__.py
slack_notifier_airflow/slack_notifier.py
slack_notifier_airflow-0.0.4.dist-info/LICENSE
slack_notifier_airflow-0.0.4.dist-info/METADATA
slack_notifier_airflow-0.0.4.dist-info/WHEEL
slack_notifier_airflow-0.0.4.dist-info/top_level.txt
slack_notifier_airflow-0.0.4.dist-info/RECORD
