Metadata-Version: 2.1
Name: slack_notifier_airflow
Version: 0.0.4
Summary: For getting alerts from airflow in a Slack channel
Home-page: https://github.com/sayatbekbolat/slack_notifier_airflow
Author: Sayat Bekbolat
Author-email: bekbolat.sayat@gmail.com
Classifier: Programming Language :: Python :: 3
Classifier: License :: OSI Approved :: MIT License
Classifier: Operating System :: OS Independent
Requires-Python: >=3.7
License-File: LICENSE
